datasette_llm_sql_writer/__init__.py
datasette_llm_sql_writer/generator.py
datasette_llm_sql_writer/static/app.js
datasette_llm_sql_writer-0.3.0.dist-info/licenses/LICENSE
datasette_llm_sql_writer-0.3.0.dist-info/METADATA
datasette_llm_sql_writer-0.3.0.dist-info/WHEEL
datasette_llm_sql_writer-0.3.0.dist-info/entry_points.txt
datasette_llm_sql_writer-0.3.0.dist-info/top_level.txt
datasette_llm_sql_writer-0.3.0.dist-info/RECORD
