Metadata-Version: 2.4
Name: datasette-llm-sql-writer
Version: 0.3.0
Summary: Generate Datasette SQL queries using plain language and an LLM
Author: Evan Jones
License-Expression: Apache-2.0
Project-URL: Homepage, https://github.com/etjones/datasette-llm-sql-writer
Project-URL: Changelog, https://github.com/etjones/datasette-llm-sql-writer/releases
Project-URL: Issues, https://github.com/etjones/datasette-llm-sql-writer/issues
Project-URL: CI, https://github.com/etjones/datasette-llm-sql-writer/actions
Classifier: Framework :: Datasette
Requires-Python: >=3.10
License-File: LICENSE
Requires-Dist: datasette>=1.0a19
Requires-Dist: llm>=0.27.1
Provides-Extra: test
Requires-Dist: pytest; extra == "test"
Requires-Dist: pytest-asyncio; extra == "test"
Requires-Dist: httpx; extra == "test"
Requires-Dist: ipython; extra == "test"
Dynamic: license-file
